petrus/__init__.py
petrus/__main__.py
petrus/_core/__init__.py
petrus/_core/api.py
petrus/_core/api_utils.py
petrus/_core/utils.py
petrus/_core/calcs/BaseCalc.py
petrus/_core/calcs/Block.py
petrus/_core/calcs/CacheCalc.py
petrus/_core/calcs/Draft.py
petrus/_core/calcs/File.py
petrus/_core/calcs/Git.py
petrus/_core/calcs/Prog.py
petrus/_core/calcs/Project.py
petrus/_core/calcs/Text.py
petrus/_core/calcs/__init__.py
petrus/_core/consts/Const.py
petrus/_core/consts/__init__.py
petrus/_core/consts/consts.toml
petrus/drafts/core.txt
petrus/drafts/gitignore.txt
petrus/drafts/init.txt
petrus/drafts/installation.txt
petrus/drafts/license.txt
petrus/drafts/main.txt
petrus/drafts/manifest.txt
petrus/drafts/test_1984.txt
petrus/drafts/tests.txt
petrus/tests/__init__.py
petrus/tests/test_1984.py
petrus-0.10.0.dist-info/licenses/LICENSE.txt
petrus-0.10.0.dist-info/METADATA
petrus-0.10.0.dist-info/WHEEL
petrus-0.10.0.dist-info/top_level.txt
petrus-0.10.0.dist-info/RECORD
