Metadata-Version: 2.4
Name: petrus
Version: 0.10.0
Summary: This project creates/autocompletes/formats a python project and upload it to PyPI.
Author-email: Johannes <johannes.programming@gmail.com>
License: The MIT License (MIT)
Project-URL: Download, https://pypi.org/project/petrus/#files
Project-URL: Index, https://pypi.org/project/petrus/
Project-URL: Source, https://github.com/johannes-programming/petrus/
Project-URL: Website, https://petrus.johannes-programming.online/
Classifier: Development Status :: 3 - Alpha
Classifier: Intended Audience :: Developers
Classifier: License :: OSI Approved :: MIT License
Classifier: Natural Language :: English
Classifier: Operating System :: OS Independent
Classifier: Programming Language :: Python
Classifier: Programming Language :: Python :: 3
Classifier: Programming Language :: Python :: 3 :: Only
Classifier: Typing :: Typed
Requires-Python: >=3.11
License-File: LICENSE.txt
Requires-Dist: beautifulsoup4<5,>=4.13.4
Requires-Dist: black<26,>=24.5
Requires-Dist: build<2,>=1.2.1
Requires-Dist: filelisting<2,>=1.2.6
Requires-Dist: funccomp<0.4,>=0.3
Requires-Dist: identityfunction<2,>=1.0.3
Requires-Dist: isort<7,>=6.0
Requires-Dist: requests<3,>=2.31
Requires-Dist: tomlhold<2,>=1.1
Requires-Dist: twine<7,>=5.2
Requires-Dist: v440<3,>=2.0a
Dynamic: license-file
